[{"name":"Hound (Fire)","mstId":448,"resourceName":"0448","rarity":4,"isEvolvable":true,"skill":{"preEvolvedSkillName":"Victorious Melody (I)","preEvolvedSkillDescription":"Increases ATK of all surviving allies in the vanguard.\\nApplies to both P.ATK and M.ATK.","preEvolvedSkillDurationSec":0,"preEvolvedSkillPreparationTimeSec":70,"preEvolvedSkillSPCost":200,"skillName":"Victorious Melody (II)","skillDescription":"Greatly increases ATK of all surviving allies in the vanguard.\\nApplies to both P.ATK and M.ATK.","skillDurationSec":0,"skillPreparationTimeSec":60,"skillSPCost":200}},{"name":"Hound (Water)","mstId":450,"resourceName":"0450","rarity":4,"isEvolvable":true,"skill":{"preEvolvedSkillName":"Victorious Melody (I)","preEvolvedSkillDescription":"Increases ATK of all surviving allies in the vanguard.\\nApplies to both P.ATK and M.ATK.","preEvolvedSkillDurationSec":0,"preEvolvedSkillPreparationTimeSec":70,"preEvolvedSkillSPCost":200,"skillName":"Victorious Melody (II)","skillDescription":"Greatly increases ATK of all surviving allies in the vanguard.\\nApplies to both P.ATK and M.ATK.","skillDurationSec":0,"skillPreparationTimeSec":60,"skillSPCost":200}},{"name":"Hound (Wind)","mstId":452,"resourceName":"0452","rarity":4,"isEvolvable":true,"skill":{"preEvolvedSkillName":"Victorious Melody (I)","preEvolvedSkillDescription":"Increases ATK of all surviving allies in the vanguard.\\nApplies to both P.ATK and M.ATK.","preEvolvedSkillDurationSec":0,"preEvolvedSkillPreparationTimeSec":70,"preEvolvedSkillSPCost":200,"skillName":"Victorious Melody (II)","skillDescription":"Greatly increases ATK of all surviving allies in the vanguard.\\nApplies to both P.ATK and M.ATK.","skillDurationSec":0,"skillPreparationTimeSec":60,"skillSPCost":200}},{"name":"Hateful Hound (Fire)","mstId":454,"resourceName":"0454","rarity":3,"isEvolvable":false,"skill":{"skillName":"Victorious Melody (II)","skillDescription":"Greatly increases ATK of all surviving allies in the vanguard.\\nApplies to both P.ATK and M.ATK.","skillDurationSec":0,"skillPreparationTimeSec":60,"skillSPCost":200}},{"name":"Hateful Hound (Water)","mstId":455,"resourceName":"0455","rarity":3,"isEvolvable":false,"skill":{"skillName":"Victorious Melody (II)","skillDescription":"Greatly increases ATK of all surviving allies in the vanguard.\\nApplies to both P.ATK and M.ATK.","skillDurationSec":0,"skillPreparationTimeSec":60,"skillSPCost":200}},{"name":"Hateful Hound (Wind)","mstId":456,"resourceName":"0456","rarity":3,"isEvolvable":false,"skill":{"skillName":"Victorious Melody (II)","skillDescription":"Greatly increases ATK of all surviving allies in the vanguard.\\nApplies to both P.ATK and M.ATK.","skillDurationSec":0,"skillPreparationTimeSec":60,"skillSPCost":200}},{"name":"Ugallu","mstId":457,"resourceName":"0457","rarity":6,"isEvolvable":true,"skill":{"preEvolvedSkillName":"Combustive Blessing (II)","preEvolvedSkillDescription":"Greatly increases the effectiveness of ally fire skills.","preEvolvedSkillDurationSec":110,"preEvolvedSkillPreparationTimeSec":90,"preEvolvedSkillSPCost":0,"skillName":"Combustive Blessing (III)","skillDescription":"Massively increases the effectiveness of ally fire skills.","skillDurationSec":120,"skillPreparationTimeSec":80,"skillSPCost":0}},{"name":"Clock Rabbit","mstId":459,"resourceName":"0459","rarity":5,"isEvolvable":true,"skill":{"preEvolvedSkillName":"Infernal Fairy Magic (II)","preEvolvedSkillDescription":"Greatly reduces the SP cost of ally fire skills.","preEvolvedSkillDurationSec":90,"preEvolvedSkillPreparationTimeSec":70,"preEvolvedSkillSPCost":200,"skillName":"Infernal Fairy Magic (III)","skillDescription":"Massively reduces the SP cost of ally fire skills.","skillDurationSec":100,"skillPreparationTimeSec":60,"skillSPCost":200}},{"name":"Plant (Fire)","mstId":461,"resourceName":"0461","rarity":4,"isEvolvable":true,"skill":{"preEvolvedSkillName":"Armor of Lamentation (I)","preEvolvedSkillDescription":"Reduces DEF of all enemies in the vanguard, even if they have fainted.\\nApplies to both P.DEF and M.DEF.","preEvolvedSkillDurationSec":0,"preEvolvedSkillPreparationTimeSec":70,"preEvolvedSkillSPCost":200,"skillName":"Armor of Lamentation (II)","skillDescription":"Greatly reduces DEF of all enemies in the vanguard, even if they have fainted.\\nApplies to both P.DEF and M.DEF.","skillDurationSec":0,"skillPreparationTimeSec":60,"skillSPCost":200}},{"name":"Plant (Water)","mstId":463,"resourceName":"0463","rarity":4,"isEvolvable":true,"skill":{"preEvolvedSkillName":"Armor of Lamentation (I)","preEvolvedSkillDescription":"Reduces DEF of all enemies in the vanguard, even if they have fainted.\\nApplies to both P.DEF and M.DEF.","preEvolvedSkillDurationSec":0,"preEvolvedSkillPreparationTimeSec":70,"preEvolvedSkillSPCost":200,"skillName":"Armor of Lamentation (II)","skillDescription":"Greatly reduces DEF of all enemies in the vanguard, even if they have fainted.\\nApplies to both P.DEF and M.DEF.","skillDurationSec":0,"skillPreparationTimeSec":60,"skillSPCost":200}},{"name":"Plant (Wind)","mstId":465,"resourceName":"0465","rarity":4,"isEvolvable":true,"skill":{"preEvolvedSkillName":"Armor of Lamentation (I)","preEvolvedSkillDescription":"Reduces DEF of all enemies in the vanguard, even if they have fainted.\\nApplies to both P.DEF and M.DEF.","preEvolvedSkillDurationSec":0,"preEvolvedSkillPreparationTimeSec":70,"preEvolvedSkillSPCost":200,"skillName":"Armor of Lamentation (II)","skillDescription":"Greatly reduces DEF of all enemies in the vanguard, even if they have fainted.\\nApplies to both P.DEF and M.DEF.","skillDurationSec":0,"skillPreparationTimeSec":60,"skillSPCost":200}},{"name":"Hateful Plant (Fire)","mstId":467,"resourceName":"0467","rarity":3,"isEvolvable":false,"skill":{"skillName":"Armor of Lamentation (II)","skillDescription":"Greatly reduces DEF of all enemies in the vanguard, even if they have fainted.\\nApplies to both P.DEF and M.DEF.","skillDurationSec":0,"skillPreparationTimeSec":60,"skillSPCost":200}},{"name":"Hateful Plant (Water)","mstId":468,"resourceName":"0468","rarity":3,"isEvolvable":false,"skill":{"skillName":"Armor of Lamentation (II)","skillDescription":"Greatly reduces DEF of all enemies in the vanguard, even if they have fainted.\\nApplies to both P.DEF and M.DEF.","skillDurationSec":0,"skillPreparationTimeSec":60,"skillSPCost":200}},{"name":"Hateful Plant (Wind)","mstId":469,"resourceName":"0469","rarity":3,"isEvolvable":false,"skill":{"skillName":"Armor of Lamentation (II)","skillDescription":"Greatly reduces DEF of all enemies in the vanguard, even if they have fainted.\\nApplies to both P.DEF and M.DEF.","skillDurationSec":0,"skillPreparationTimeSec":60,"skillSPCost":200}},{"name":"Golem (Fire)","mstId":470,"resourceName":"0470","rarity":4,"isEvolvable":true,"skill":{"preEvolvedSkillName":"Blessed Armor (I)","preEvolvedSkillDescription":"Increases DEF of all surviving allies in the vanguard.\\nApplies to both P.DEF and M.DEF.","preEvolvedSkillDurationSec":0,"preEvolvedSkillPreparationTimeSec":70,"preEvolvedSkillSPCost":200,"skillName":"Blessed Armor (II)","skillDescription":"Greatly increases DEF of all surviving allies in the vanguard.\\nApplies to both P.DEF and M.DEF.","skillDurationSec":0,"skillPreparationTimeSec":60,"skillSPCost":200}},{"name":"Golem (Water)","mstId":472,"resourceName":"0472","rarity":4,"isEvolvable":true,"skill":{"preEvolvedSkillName":"Blessed Armor (I)","preEvolvedSkillDescription":"Increases DEF of all surviving allies in the vanguard.\\nApplies to both P.DEF and M.DEF.","preEvolvedSkillDurationSec":0,"preEvolvedSkillPreparationTimeSec":70,"preEvolvedSkillSPCost":200,"skillName":"Blessed Armor (II)","skillDescription":"Greatly increases DEF of all surviving allies in the vanguard.\\nApplies to both P.DEF and M.DEF.","skillDurationSec":0,"skillPreparationTimeSec":60,"skillSPCost":200}},{"name":"Golem (Wind)","mstId":474,"resourceName":"0474","rarity":4,"isEvolvable":true,"skill":{"preEvolvedSkillName":"Blessed Armor (I)","preEvolvedSkillDescription":"Increases DEF of all surviving allies in the vanguard.\\nApplies to both P.DEF and M.DEF.","preEvolvedSkillDurationSec":0,"preEvolvedSkillPreparationTimeSec":70,"preEvolvedSkillSPCost":200,"skillName":"Blessed Armor (II)","skillDescription":"Greatly increases DEF of all surviving allies in the vanguard.\\nApplies to both P.DEF and M.DEF.","skillDurationSec":0,"skillPreparationTimeSec":60,"skillSPCost":200}},{"name":"Hateful Golem (Fire)","mstId":476,"resourceName":"0476","rarity":3,"isEvolvable":false,"skill":{"skillName":"Blessed Armor (II)","skillDescription":"Greatly increases DEF of all surviving allies in the vanguard.\\nApplies to both P.DEF and M.DEF.","skillDurationSec":0,"skillPreparationTimeSec":60,"skillSPCost":200}},{"name":"Hateful Golem (Water)","mstId":477,"resourceName":"0477","rarity":3,"isEvolvable":false,"skill":{"skillName":"Blessed Armor (II)","skillDescription":"Greatly increases DEF of all surviving allies in the vanguard.\\nApplies to both P.DEF and M.DEF.","skillDurationSec":0,"skillPreparationTimeSec":60,"skillSPCost":200}},{"name":"Hateful Golem (Wind)","mstId":478,"resourceName":"0478","rarity":3,"isEvolvable":false,"skill":{"skillName":"Blessed Armor (II)","skillDescription":"Greatly increases DEF of all surviving allies in the vanguard.\\nApplies to both P.DEF and M.DEF.","skillDurationSec":0,"skillPreparationTimeSec":60,"skillSPCost":200}},{"name":"Freeze Golem","mstId":479,"resourceName":"0479","rarity":6,"isEvolvable":true,"skill":{"preEvolvedSkillName":"Aqueous Blessing (II)","preEvolvedSkillDescription":"Greatly increases the effectiveness of ally water skills.","preEvolvedSkillDurationSec":110,"preEvolvedSkillPreparationTimeSec":90,"preEvolvedSkillSPCost":0,"skillName":"Aqueous Blessing (III)","skillDescription":"Massively increases the effectiveness of ally water skills.","skillDurationSec":120,"skillPreparationTimeSec":80,"skillSPCost":0}},{"name":"Bird (Fire)","mstId":483,"resourceName":"0483","rarity":4,"isEvolvable":true,"skill":{"preEvolvedSkillName":"Begrudging Blade (I)","preEvolvedSkillDescription":"Reduces ATK of all enemies in the vanguard, even if they have fainted.\\nApplies to both P.ATK and M.ATK.","preEvolvedSkillDurationSec":0,"preEvolvedSkillPreparationTimeSec":70,"preEvolvedSkillSPCost":200,"skillName":"Begrudging Blade (II)","skillDescription":"Greatly reduces ATK of all enemies in the vanguard, even if they have fainted.\\nApplies to both P.ATK and M.ATK.","skillDurationSec":0,"skillPreparationTimeSec":60,"skillSPCost":200}},{"name":"Bird (Water)","mstId":485,"resourceName":"0485","rarity":4,"isEvolvable":true,"skill":{"preEvolvedSkillName":"Begrudging Blade (I)","preEvolvedSkillDescription":"Reduces ATK of all enemies in the vanguard, even if they have fainted.\\nApplies to both P.ATK and M.ATK.","preEvolvedSkillDurationSec":0,"preEvolvedSkillPreparationTimeSec":70,"preEvolvedSkillSPCost":200,"skillName":"Begrudging Blade (II)","skillDescription":"Greatly reduces ATK of all enemies in the vanguard, even if they have fainted.\\nApplies to both P.ATK and M.ATK.","skillDurationSec":0,"skillPreparationTimeSec":60,"skillSPCost":200}},{"name":"Bird (Wind)","mstId":487,"resourceName":"0487","rarity":4,"isEvolvable":true,"skill":{"preEvolvedSkillName":"Begrudging Blade (I)","preEvolvedSkillDescription":"Reduces ATK of all enemies in the vanguard, even if they have fainted.\\nApplies to both P.ATK and M.ATK.","preEvolvedSkillDurationSec":0,"preEvolvedSkillPreparationTimeSec":70,"preEvolvedSkillSPCost":200,"skillName":"Begrudging Blade (II)","skillDescription":"Greatly reduces ATK of all enemies in the vanguard, even if they have fainted.\\nApplies to both P.ATK and M.ATK.","skillDurationSec":0,"skillPreparationTimeSec":60,"skillSPCost":200}},{"name":"Hateful Bird (Fire)","mstId":489,"resourceName":"0489","rarity":3,"isEvolvable":false,"skill":{"skillName":"Begrudging Blade (II)","skillDescription":"Greatly reduces ATK of all enemies in the vanguard, even if they have fainted.\\nApplies to both P.ATK and M.ATK.","skillDurationSec":0,"skillPreparationTimeSec":60,"skillSPCost":200}},{"name":"Hateful Bird (Water)","mstId":490,"resourceName":"0490","rarity":3,"isEvolvable":false,"skill":{"skillName":"Begrudging Blade (II)","skillDescription":"Greatly reduces ATK of all enemies in the vanguard, even if they have fainted.\\nApplies to both P.ATK and M.ATK.","skillDurationSec":0,"skillPreparationTimeSec":60,"skillSPCost":200}},{"name":"Hateful Bird (Wind)","mstId":491,"resourceName":"0491","rarity":3,"isEvolvable":false,"skill":{"skillName":"Begrudging Blade (II)","skillDescription":"Greatly reduces ATK of all enemies in the vanguard, even if they have fainted.\\nApplies to both P.ATK and M.ATK.","skillDurationSec":0,"skillPreparationTimeSec":60,"skillSPCost":200}},{"name":"Ghost (Fire)","mstId":494,"resourceName":"0494","rarity":4,"isEvolvable":true,"skill":{"preEvolvedSkillName":"Infernal Fairy Magic (I)","preEvolvedSkillDescription":"Reduces the SP cost of ally fire skills.","preEvolvedSkillDurationSec":80,"preEvolvedSkillPreparationTimeSec":80,"preEvolvedSkillSPCost":200,"skillName":"Infernal Fairy Magic (II)","skillDescription":"Greatly reduces the SP cost of ally fire skills.","skillDurationSec":90,"skillPreparationTimeSec":70,"skillSPCost":200}},{"name":"Ghost (Water)","mstId":496,"resourceName":"0496","rarity":4,"isEvolvable":true,"skill":{"preEvolvedSkillName":"Tidal Fairy Magic (I)","preEvolvedSkillDescription":"Reduces the SP cost of ally water skills.","preEvolvedSkillDurationSec":80,"preEvolvedSkillPreparationTimeSec":80,"preEvolvedSkillSPCost":200,"skillName":"Tidal Fairy Magic (II)","skillDescription":"Greatly reduces the SP cost of ally water skills.","skillDurationSec":90,"skillPreparationTimeSec":70,"skillSPCost":200}},{"name":"Ghost (Wind)","mstId":498,"resourceName":"0498","rarity":4,"isEvolvable":true,"skill":{"preEvolvedSkillName":"Zephyr Fairy Magic (I)","preEvolvedSkillDescription":"Reduces the SP cost of ally wind skills.","preEvolvedSkillDurationSec":80,"preEvolvedSkillPreparationTimeSec":80,"preEvolvedSkillSPCost":200,"skillName":"Zephyr Fairy Magic (II)","skillDescription":"Greatly reduces the SP cost of ally wind skills.","skillDurationSec":90,"skillPreparationTimeSec":70,"skillSPCost":200}},{"name":"Hateful Ghost (Fire)","mstId":500,"resourceName":"0500","rarity":3,"isEvolvable":false,"skill":{"skillName":"Infernal Fairy Magic (II)","skillDescription":"Greatly reduces the SP cost of ally fire skills.","skillDurationSec":90,"skillPreparationTimeSec":70,"skillSPCost":200}},{"name":"Hateful Ghost (Water)","mstId":501,"resourceName":"0501","rarity":3,"isEvolvable":false,"skill":{"skillName":"Tidal Fairy Magic (II)","skillDescription":"Greatly reduces the SP cost of ally water skills.","skillDurationSec":90,"skillPreparationTimeSec":70,"skillSPCost":200}},{"name":"Hateful Ghost (Wind)","mstId":502,"resourceName":"0502","rarity":3,"isEvolvable":false,"skill":{"skillName":"Zephyr Fairy Magic (II)","skillDescription":"Greatly reduces the SP cost of ally wind skills.","skillDurationSec":90,"skillPreparationTimeSec":70,"skillSPCost":200}},{"name":"強化ゴースト(剣)","mstId":503,"resourceName":"0503","rarity":3,"isEvolvable":false,"skill":{"skillName":"Victorious Melody (I)","skillDescription":"Increases ATK of all surviving allies in the vanguard.\\nApplies to both P.ATK and M.ATK.","skillDurationSec":0,"skillPreparationTimeSec":70,"skillSPCost":200}},{"name":"強化ハイゴースト(剣)","mstId":504,"resourceName":"0504","rarity":3,"isEvolvable":false,"skill":{"skillName":"Victorious Melody (II)","skillDescription":"Greatly increases ATK of all surviving allies in the vanguard.\\nApplies to both P.ATK and M.ATK.","skillDurationSec":0,"skillPreparationTimeSec":60,"skillSPCost":200}},{"name":"強化ゴースト(盾)","mstId":505,"resourceName":"0505","rarity":3,"isEvolvable":false,"skill":{"skillName":"Blessed Armor (I)","skillDescription":"Increases DEF of all surviving allies in the vanguard.\\nApplies to both P.DEF and M.DEF.","skillDurationSec":0,"skillPreparationTimeSec":70,"skillSPCost":200}},{"name":"強化ハイゴースト(盾)","mstId":506,"resourceName":"0506","rarity":3,"isEvolvable":false,"skill":{"skillName":"Blessed Armor (II)","skillDescription":"Greatly increases DEF of all surviving allies in the vanguard.\\nApplies to both P.DEF and M.DEF.","skillDurationSec":0,"skillPreparationTimeSec":60,"skillSPCost":200}},{"name":"Lizard (Fire)","mstId":507,"resourceName":"0507","rarity":4,"isEvolvable":true,"skill":{"preEvolvedSkillName":"Combustive Blessing (I)","preEvolvedSkillDescription":"Increases the effectiveness of ally fire skills.","preEvolvedSkillDurationSec":100,"preEvolvedSkillPreparationTimeSec":100,"preEvolvedSkillSPCost":200,"skillName":"Combustive Blessing (II)","skillDescription":"Greatly increases the effectiveness of ally fire skills.","skillDurationSec":110,"skillPreparationTimeSec":90,"skillSPCost":200}},{"name":"Lizard (Water)","mstId":509,"resourceName":"0509","rarity":4,"isEvolvable":true,"skill":{"preEvolvedSkillName":"Aqueous Blessing (I)","preEvolvedSkillDescription":"Increases the effectiveness of ally water skills.","preEvolvedSkillDurationSec":100,"preEvolvedSkillPreparationTimeSec":100,"preEvolvedSkillSPCost":200,"skillName":"Aqueous Blessing (II)","skillDescription":"Greatly increases the effectiveness of ally water skills.","skillDurationSec":110,"skillPreparationTimeSec":90,"skillSPCost":200}},{"name":"Lizard (Wind)","mstId":511,"resourceName":"0511","rarity":4,"isEvolvable":true,"skill":{"preEvolvedSkillName":"Gale Blessing (I)","preEvolvedSkillDescription":"Increases the effectiveness of ally wind skills.","preEvolvedSkillDurationSec":100,"preEvolvedSkillPreparationTimeSec":100,"preEvolvedSkillSPCost":200,"skillName":"Gale Blessing (II)","skillDescription":"Greatly increases the effectiveness of ally wind skills.","skillDurationSec":110,"skillPreparationTimeSec":90,"skillSPCost":200}},{"name":"Hateful Lizard (Fire)","mstId":513,"resourceName":"0513","rarity":3,"isEvolvable":false,"skill":{"skillName":"Combustive Blessing (II)","skillDescription":"Greatly increases the effectiveness of ally fire skills.","skillDurationSec":110,"skillPreparationTimeSec":90,"skillSPCost":200}},{"name":"Hateful Lizard (Water)","mstId":514,"resourceName":"0514","rarity":3,"isEvolvable":false,"skill":{"skillName":"Aqueous Blessing (II)","skillDescription":"Greatly increases the effectiveness of ally water skills.","skillDurationSec":110,"skillPreparationTimeSec":90,"skillSPCost":200}},{"name":"Hateful Lizard (Wind)","mstId":515,"resourceName":"0515","rarity":3,"isEvolvable":false,"skill":{"skillName":"Gale Blessing (II)","skillDescription":"Greatly increases the effectiveness of ally wind skills.","skillDurationSec":110,"skillPreparationTimeSec":90,"skillSPCost":200}},{"name":"Lindwyrm","mstId":516,"resourceName":"0516","rarity":6,"isEvolvable":true,"skill":{"preEvolvedSkillName":"Gale Blessing (II)","preEvolvedSkillDescription":"Greatly increases the effectiveness of ally wind skills.","preEvolvedSkillDurationSec":110,"preEvolvedSkillPreparationTimeSec":90,"preEvolvedSkillSPCost":0,"skillName":"Gale Blessing (III)","skillDescription":"Massively increases the effectiveness of ally wind skills.","skillDurationSec":120,"skillPreparationTimeSec":80,"skillSPCost":0}},{"name":"Orc (Fire)","mstId":518,"resourceName":"0518","rarity":4,"isEvolvable":true,"skill":{"preEvolvedSkillName":"Defiant Roar (I)","preEvolvedSkillDescription":"Note: Increases the effectiveness of all vanguard ally attack skills.\\nEffective only when your lifeforce is lower than the enemy's during a combo chance.","preEvolvedSkillDurationSec":100,"preEvolvedSkillPreparationTimeSec":80,"preEvolvedSkillSPCost":200,"skillName":"Defiant Roar (II)","skillDescription":"Greatly increases the effectiveness of all vanguard ally attack skills.\\nEffective only when at a disadvantage during a combo chance.","skillDurationSec":110,"skillPreparationTimeSec":70,"skillSPCost":200}},{"name":"Orc (Water)","mstId":520,"resourceName":"0520","rarity":4,"isEvolvable":true,"skill":{"preEvolvedSkillName":"Defiant Roar (I)","preEvolvedSkillDescription":"Note: Increases the effectiveness of all vanguard ally attack skills.\\nEffective only when your lifeforce is lower than the enemy's during a combo chance.","preEvolvedSkillDurationSec":100,"preEvolvedSkillPreparationTimeSec":80,"preEvolvedSkillSPCost":200,"skillName":"Defiant Roar (II)","skillDescription":"Greatly increases the effectiveness of all vanguard ally attack skills.\\nEffective only when at a disadvantage during a combo chance.","skillDurationSec":110,"skillPreparationTimeSec":70,"skillSPCost":200}},{"name":"Orc (Wind)","mstId":522,"resourceName":"0522","rarity":4,"isEvolvable":true,"skill":{"preEvolvedSkillName":"Defiant Roar (I)","preEvolvedSkillDescription":"Note: Increases the effectiveness of all vanguard ally attack skills.\\nEffective only when your lifeforce is lower than the enemy's during a combo chance.","preEvolvedSkillDurationSec":100,"preEvolvedSkillPreparationTimeSec":80,"preEvolvedSkillSPCost":200,"skillName":"Defiant Roar (II)","skillDescription":"Greatly increases the effectiveness of all vanguard ally attack skills.\\nEffective only when at a disadvantage during a combo chance.","skillDurationSec":110,"skillPreparationTimeSec":70,"skillSPCost":200}},{"name":"Hateful Orc (Fire)","mstId":524,"resourceName":"0524","rarity":3,"isEvolvable":false,"skill":{"skillName":"Defiant Roar (II)","skillDescription":"Greatly increases the effectiveness of all vanguard ally attack skills.\\nEffective only when at a disadvantage during a combo chance.","skillDurationSec":110,"skillPreparationTimeSec":70,"skillSPCost":200}},{"name":"Hateful Orc (Water)","mstId":525,"resourceName":"0525","rarity":3,"isEvolvable":false,"skill":{"skillName":"Defiant Roar (II)","skillDescription":"Greatly increases the effectiveness of all vanguard ally attack skills.\\nEffective only when at a disadvantage during a combo chance.","skillDurationSec":110,"skillPreparationTimeSec":70,"skillSPCost":200}},{"name":"Hateful Orc (Wind)","mstId":526,"resourceName":"0526","rarity":3,"isEvolvable":false,"skill":{"skillName":"Defiant Roar (II)","skillDescription":"Greatly increases the effectiveness of all vanguard ally attack skills.\\nEffective only when at a disadvantage during a combo chance.","skillDurationSec":110,"skillPreparationTimeSec":70,"skillSPCost":200}},{"name":"Spider (Fire)","mstId":527,"resourceName":"0527","rarity":4,"isEvolvable":true,"skill":{"preEvolvedSkillName":"Defiant Roar (I)","preEvolvedSkillDescription":"Note: Increases the effectiveness of all vanguard ally attack skills.\\nEffective only when your lifeforce is lower than the enemy's during a combo chance.","preEvolvedSkillDurationSec":100,"preEvolvedSkillPreparationTimeSec":80,"preEvolvedSkillSPCost":200,"skillName":"Defiant Roar (II)","skillDescription":"Greatly increases the effectiveness of all vanguard ally attack skills.\\nEffective only when at a disadvantage during a combo chance.","skillDurationSec":110,"skillPreparationTimeSec":70,"skillSPCost":200}},{"name":"Spider (Water)","mstId":529,"resourceName":"0529","rarity":4,"isEvolvable":true,"skill":{"preEvolvedSkillName":"Defiant Roar (I)","preEvolvedSkillDescription":"Note: Increases the effectiveness of all vanguard ally attack skills.\\nEffective only when your lifeforce is lower than the enemy's during a combo chance.","preEvolvedSkillDurationSec":100,"preEvolvedSkillPreparationTimeSec":80,"preEvolvedSkillSPCost":200,"skillName":"Defiant Roar (II)","skillDescription":"Greatly increases the effectiveness of all vanguard ally attack skills.\\nEffective only when at a disadvantage during a combo chance.","skillDurationSec":110,"skillPreparationTimeSec":70,"skillSPCost":200}},{"name":"Spider (Wind)","mstId":531,"resourceName":"0531","rarity":4,"isEvolvable":true,"skill":{"preEvolvedSkillName":"Defiant Roar (I)","preEvolvedSkillDescription":"Note: Increases the effectiveness of all vanguard ally attack skills.\\nEffective only when your lifeforce is lower than the enemy's during a combo chance.","preEvolvedSkillDurationSec":100,"preEvolvedSkillPreparationTimeSec":80,"preEvolvedSkillSPCost":200,"skillName":"Defiant Roar (II)","skillDescription":"Greatly increases the effectiveness of all vanguard ally attack skills.\\nEffective only when at a disadvantage during a combo chance.","skillDurationSec":110,"skillPreparationTimeSec":70,"skillSPCost":200}},{"name":"Hateful Spider (Fire)","mstId":533,"resourceName":"0533","rarity":3,"isEvolvable":false,"skill":{"skillName":"Defiant Roar (II)","skillDescription":"Greatly increases the effectiveness of all vanguard ally attack skills.\\nEffective only when at a disadvantage during a combo chance.","skillDurationSec":110,"skillPreparationTimeSec":70,"skillSPCost":200}},{"name":"Hateful Spider (Water)","mstId":534,"resourceName":"0534","rarity":3,"isEvolvable":false,"skill":{"skillName":"Defiant Roar (II)","skillDescription":"Greatly increases the effectiveness of all vanguard ally attack skills.\\nEffective only when at a disadvantage during a combo chance.","skillDurationSec":110,"skillPreparationTimeSec":70,"skillSPCost":200}},{"name":"Hateful Spider (Wind)","mstId":535,"resourceName":"0535","rarity":3,"isEvolvable":false,"skill":{"skillName":"Defiant Roar (II)","skillDescription":"Greatly increases the effectiveness of all vanguard ally attack skills.\\nEffective only when at a disadvantage during a combo chance.","skillDurationSec":110,"skillPreparationTimeSec":70,"skillSPCost":200}},{"name":"Absorbent Spider","mstId":536,"resourceName":"0536","rarity":5,"isEvolvable":true,"skill":{"preEvolvedSkillName":"Defiant Roar (I)","preEvolvedSkillDescription":"Note: Increases the effectiveness of all vanguard ally attack skills.\\nEffective only when your lifeforce is lower than the enemy's during a combo chance.","preEvolvedSkillDurationSec":100,"preEvolvedSkillPreparationTimeSec":80,"preEvolvedSkillSPCost":200,"skillName":"Defiant Roar (II)","skillDescription":"Greatly increases the effectiveness of all vanguard ally attack skills.\\nEffective only when at a disadvantage during a combo chance.","skillDurationSec":110,"skillPreparationTimeSec":70,"skillSPCost":200}},{"name":"Shield Wisp (Fire)","mstId":538,"resourceName":"0538","rarity":4,"isEvolvable":false,"skill":{"skillName":"Infernal Fairy Magic (III)","skillDescription":"Massively reduces the SP cost of ally fire skills.","skillDurationSec":100,"skillPreparationTimeSec":60,"skillSPCost":200}},{"name":"Shield Wisp (Water)","mstId":539,"resourceName":"0539","rarity":4,"isEvolvable":false,"skill":{"skillName":"Tidal Fairy Magic (III)","skillDescription":"Massively reduces the SP cost of ally water skills.","skillDurationSec":100,"skillPreparationTimeSec":60,"skillSPCost":200}},{"name":"Shield Wisp (Wind)","mstId":540,"resourceName":"0540","rarity":4,"isEvolvable":false,"skill":{"skillName":"Zephyr Fairy Magic (III)","skillDescription":"Massively reduces the SP cost of ally wind skills.","skillDurationSec":100,"skillPreparationTimeSec":60,"skillSPCost":200}},{"name":"Snake (Fire)","mstId":541,"resourceName":"0541","rarity":4,"isEvolvable":true,"skill":{"preEvolvedSkillName":"Engulfing Shout (I)","preEvolvedSkillDescription":"Reduces the effectiveness of enemy fire skills.\\nThis summon skill ends when your lifeforce drops below half of that of the enemy.","preEvolvedSkillDurationSec":80,"preEvolvedSkillPreparationTimeSec":70,"preEvolvedSkillSPCost":200,"skillName":"Engulfing Shout (II)","skillDescription":"Greatly reduces the effectiveness of enemy fire skills.\\nThis summon skill ends when your lifeforce drops below half of that of the enemy.","skillDurationSec":90,"skillPreparationTimeSec":60,"skillSPCost":200}},{"name":"Snake (Water)","mstId":543,"resourceName":"0543","rarity":4,"isEvolvable":true,"skill":{"preEvolvedSkillName":"Cry of the Damned (I)","preEvolvedSkillDescription":"Reduces the effectiveness of enemy water skills.\\nThis summon skill ends when your lifeforce drops below half of that of the enemy.","preEvolvedSkillDurationSec":80,"preEvolvedSkillPreparationTimeSec":70,"preEvolvedSkillSPCost":200,"skillName":"Cry of the Damned (II)","skillDescription":"Greatly reduces the effectiveness of enemy water skills.\\nThis summon skill ends when your lifeforce drops below half of that of the enemy.","skillDurationSec":90,"skillPreparationTimeSec":60,"skillSPCost":200}},{"name":"Snake (Wind)","mstId":545,"resourceName":"0545","rarity":4,"isEvolvable":true,"skill":{"preEvolvedSkillName":"Soothing Command (I)","preEvolvedSkillDescription":"Reduces the effectiveness of enemy wind skills.\\nThis summon skill ends when your lifeforce drops below half of that of the enemy.","preEvolvedSkillDurationSec":80,"preEvolvedSkillPreparationTimeSec":70,"preEvolvedSkillSPCost":200,"skillName":"Soothing Command (II)","skillDescription":"Greatly reduces the effectiveness of enemy wind skills.\\nThis summon skill ends when your lifeforce drops below half of that of the enemy.","skillDurationSec":90,"skillPreparationTimeSec":60,"skillSPCost":200}},{"name":"Hateful Snake (Fire)","mstId":547,"resourceName":"0547","rarity":3,"isEvolvable":false,"skill":{"skillName":"Engulfing Shout (II)","skillDescription":"Greatly reduces the effectiveness of enemy fire skills.\\nThis summon skill ends when your lifeforce drops below half of that of the enemy.","skillDurationSec":90,"skillPreparationTimeSec":60,"skillSPCost":200}},{"name":"Hateful Snake (Water)","mstId":548,"resourceName":"0548","rarity":3,"isEvolvable":false,"skill":{"skillName":"Cry of the Damned (II)","skillDescription":"Greatly reduces the effectiveness of enemy water skills.\\nThis summon skill ends when your lifeforce drops below half of that of the enemy.","skillDurationSec":90,"skillPreparationTimeSec":60,"skillSPCost":200}},{"name":"Hateful Snake (Wind)","mstId":549,"resourceName":"0549","rarity":3,"isEvolvable":false,"skill":{"skillName":"Soothing Command (II)","skillDescription":"Greatly reduces the effectiveness of enemy wind skills.\\nThis summon skill ends when your lifeforce drops below half of that of the enemy.","skillDurationSec":90,"skillPreparationTimeSec":60,"skillSPCost":200}},{"name":"Jörmungandr","mstId":550,"resourceName":"0550","rarity":6,"isEvolvable":true,"skill":{"preEvolvedSkillName":"Uplifting Chant (II)","preEvolvedSkillDescription":"Greatly increases the activation rate of ally support skills.","preEvolvedSkillDurationSec":110,"preEvolvedSkillPreparationTimeSec":90,"preEvolvedSkillSPCost":200,"skillName":"Uplifting Chant (III)","skillDescription":"Massively increases the activation rate of ally support skills.","skillDurationSec":120,"skillPreparationTimeSec":80,"skillSPCost":200}},{"name":"Drizella, the Jealous Serpent","mstId":553,"resourceName":"0553","rarity":5,"isEvolvable":true,"skill":{"preEvolvedSkillName":"Tidal Fairy Magic (II)","preEvolvedSkillDescription":"Greatly reduces the SP cost of ally water skills.","preEvolvedSkillDurationSec":90,"preEvolvedSkillPreparationTimeSec":70,"preEvolvedSkillSPCost":200,"skillName":"Tidal Fairy Magic (III)","skillDescription":"Massively reduces the SP cost of ally water skills.","skillDurationSec":100,"skillPreparationTimeSec":60,"skillSPCost":200}},{"name":"Gluttonous Eris","mstId":557,"resourceName":"0557","rarity":6,"isEvolvable":true,"skill":{"preEvolvedSkillName":"Fairy King Magic (II)","preEvolvedSkillDescription":"Greatly reduces the SP cost of ally skills of any affinity.","preEvolvedSkillDurationSec":110,"preEvolvedSkillPreparationTimeSec":70,"preEvolvedSkillSPCost":0,"skillName":"Fairy King Magic (III)","skillDescription":"Massively reduces the SP cost of ally skills of any affinity.","skillDurationSec":120,"skillPreparationTimeSec":60,"skillSPCost":0}},{"name":"Nightmare (Bondage)","mstId":559,"resourceName":"0559","rarity":4,"isEvolvable":false,"skill":{"skillName":"Aqueous Blessing (II)","skillDescription":"Greatly increases the effectiveness of ally water skills.","skillDurationSec":110,"skillPreparationTimeSec":90,"skillSPCost":200}},{"name":"Nightmare (Justice)","mstId":560,"resourceName":"0560","rarity":4,"isEvolvable":false,"skill":{"skillName":"Defiant Roar (II)","skillDescription":"Greatly increases the effectiveness of all vanguard ally attack skills.\\nEffective only when at a disadvantage during a combo chance.","skillDurationSec":110,"skillPreparationTimeSec":70,"skillSPCost":200}},{"name":"Nightmare (Brutality)","mstId":561,"resourceName":"0561","rarity":4,"isEvolvable":false,"skill":{"skillName":"Combustive Blessing (II)","skillDescription":"Greatly increases the effectiveness of ally fire skills.","skillDurationSec":110,"skillPreparationTimeSec":90,"skillSPCost":200}},{"name":"Nightmare (Depravity)","mstId":562,"resourceName":"0562","rarity":4,"isEvolvable":false,"skill":{"skillName":"Engulfing Shout (II)","skillDescription":"Greatly reduces the effectiveness of enemy fire skills.\\nThis summon skill ends when your lifeforce drops below half of that of the enemy.","skillDurationSec":90,"skillPreparationTimeSec":60,"skillSPCost":200}},{"name":"Nightmare (Depravity)","mstId":563,"resourceName":"0563","rarity":4,"isEvolvable":false,"skill":{"skillName":"Engulfing Shout (II)","skillDescription":"Greatly reduces the effectiveness of enemy fire skills.\\nThis summon skill ends when your lifeforce drops below half of that of the enemy.","skillDurationSec":90,"skillPreparationTimeSec":60,"skillSPCost":200}},{"name":"Nightmare (Dependence)","mstId":564,"resourceName":"0564","rarity":4,"isEvolvable":false,"skill":{"skillName":"Gale Blessing (II)","skillDescription":"Greatly increases the effectiveness of ally wind skills.","skillDurationSec":110,"skillPreparationTimeSec":90,"skillSPCost":200}},{"name":"Nightmare (Delusion)","mstId":567,"resourceName":"0567","rarity":4,"isEvolvable":false,"skill":{"skillName":"Soothing Command (II)","skillDescription":"Greatly reduces the effectiveness of enemy wind skills.\\nThis summon skill ends when your lifeforce drops below half of that of the enemy.","skillDurationSec":90,"skillPreparationTimeSec":60,"skillSPCost":200}},{"name":"Nightmare (Delusion)","mstId":568,"resourceName":"0568","rarity":4,"isEvolvable":false,"skill":{"skillName":"Soothing Command (II)","skillDescription":"Greatly reduces the effectiveness of enemy wind skills.\\nThis summon skill ends when your lifeforce drops below half of that of the enemy.","skillDurationSec":90,"skillPreparationTimeSec":60,"skillSPCost":200}},{"name":"Nightmare (Languor)","mstId":569,"resourceName":"0569","rarity":4,"isEvolvable":false,"skill":{"skillName":"Zephyr Fairy Magic (II)","skillDescription":"Greatly reduces the SP cost of ally wind skills.","skillDurationSec":90,"skillPreparationTimeSec":70,"skillSPCost":200}},{"name":"Nightmare (Languor)","mstId":570,"resourceName":"0570","rarity":4,"isEvolvable":false,"skill":{"skillName":"Zephyr Fairy Magic (II)","skillDescription":"Greatly reduces the SP cost of ally wind skills.","skillDurationSec":90,"skillPreparationTimeSec":70,"skillSPCost":200}},{"name":"Nightmare (Masochism)","mstId":571,"resourceName":"0571","rarity":4,"isEvolvable":false,"skill":{"skillName":"Cry of the Damned (II)","skillDescription":"Greatly reduces the effectiveness of enemy water skills.\\nThis summon skill ends when your lifeforce drops below half of that of the enemy.","skillDurationSec":90,"skillPreparationTimeSec":60,"skillSPCost":200}},{"name":"Nightmare (Masochism)","mstId":572,"resourceName":"0572","rarity":4,"isEvolvable":false,"skill":{"skillName":"Cry of the Damned (II)","skillDescription":"Greatly reduces the effectiveness of enemy water skills.\\nThis summon skill ends when your lifeforce drops below half of that of the enemy.","skillDurationSec":90,"skillPreparationTimeSec":60,"skillSPCost":200}},{"name":"Fina, the Loyal Falsehood","mstId":583,"resourceName":"0583","rarity":5,"isEvolvable":true,"skill":{"preEvolvedSkillName":"Song of Camaraderie (I)","preEvolvedSkillDescription":"Increases ATK of all surviving allies in the vanguard.\\nApplies to both P.ATK and M.ATK.","preEvolvedSkillDurationSec":0,"preEvolvedSkillPreparationTimeSec":60,"preEvolvedSkillSPCost":200,"skillName":"Song of Camaraderie (II)","skillDescription":"Greatly increases ATK of all surviving allies in the vanguard.\\nApplies to both P.ATK and M.ATK.","skillDurationSec":0,"skillPreparationTimeSec":50,"skillSPCost":200}},{"name":"Digitalis, the Undertaker","mstId":639,"resourceName":"0639","rarity":6,"isEvolvable":true,"skill":{"preEvolvedSkillName":"Cry of the Damned (II)","preEvolvedSkillDescription":"Greatly reduces the effectiveness of enemy water skills.\\nThis summon skill ends when your lifeforce drops below half of that of the enemy.","preEvolvedSkillDurationSec":90,"preEvolvedSkillPreparationTimeSec":60,"preEvolvedSkillSPCost":0,"skillName":"Cry of the Damned (III)","skillDescription":"Massively reduces the effectiveness of enemy water skills.\\nThis summon skill ends when your lifeforce drops below half of that of the enemy.","skillDurationSec":100,"skillPreparationTimeSec":50,"skillSPCost":0}},{"name":"Solitary Black Rabbit","mstId":663,"resourceName":"0663","rarity":5,"isEvolvable":true,"skill":{"preEvolvedSkillName":"Victorious Melody (II)","preEvolvedSkillDescription":"Greatly increases ATK of all surviving allies in the vanguard.\\nApplies to both P.ATK and M.ATK.","preEvolvedSkillDurationSec":0,"preEvolvedSkillPreparationTimeSec":60,"preEvolvedSkillSPCost":200,"skillName":"Victorious Melody (III)","skillDescription":"Massively increases ATK of all surviving allies in the vanguard.\\nApplies to both P.ATK and M.ATK.","skillDurationSec":0,"skillPreparationTimeSec":50,"skillSPCost":200}},{"name":"Fafnir","mstId":665,"resourceName":"0665","rarity":6,"isEvolvable":true,"skill":{"preEvolvedSkillName":"Combustive Blessing (II)","preEvolvedSkillDescription":"Greatly increases the effectiveness of ally fire skills.","preEvolvedSkillDurationSec":110,"preEvolvedSkillPreparationTimeSec":90,"preEvolvedSkillSPCost":200,"skillName":"Combustive Blessing (III)","skillDescription":"Massively increases the effectiveness of ally fire skills.","skillDurationSec":120,"skillPreparationTimeSec":80,"skillSPCost":200}},{"name":"Tricky Wisp","mstId":667,"resourceName":"0667","rarity":6,"isEvolvable":true,"skill":{"preEvolvedSkillName":"Enchanted Armor (I)","preEvolvedSkillDescription":"Increases DEF of all surviving allies in the vanguard.\\nApplies to both P.DEF and M.DEF.","preEvolvedSkillDurationSec":0,"preEvolvedSkillPreparationTimeSec":60,"preEvolvedSkillSPCost":200,"skillName":"Enchanted Armor (II)","skillDescription":"Greatly increases DEF of all surviving allies in the vanguard.\\nApplies to both P.DEF and M.DEF.","skillDurationSec":0,"skillPreparationTimeSec":50,"skillSPCost":200}},{"name":"Noin, Sandstorm's Mandate","mstId":743,"resourceName":"0743","rarity":6,"isEvolvable":true,"skill":{"preEvolvedSkillName":"Hindering Wail (II)","preEvolvedSkillDescription":"Greatly reduces the activation rate of enemy support skills.\\nThis summon skill ends when there are less than 2 minutes left in the Colosseum.","preEvolvedSkillDurationSec":90,"preEvolvedSkillPreparationTimeSec":60,"preEvolvedSkillSPCost":0,"skillName":"Hindering Wail (III)","skillDescription":"Massively reduces the activation rate of enemy support skills.\\nThis summon skill ends when there are less than 2 minutes left in the Colosseum.","skillDurationSec":100,"skillPreparationTimeSec":50,"skillSPCost":0}},{"name":"Phoenix","mstId":769,"resourceName":"0769","rarity":5,"isEvolvable":true,"skill":{"preEvolvedSkillName":"Combustive Blessing (I)","preEvolvedSkillDescription":"Increases the effectiveness of ally fire skills.","preEvolvedSkillDurationSec":100,"preEvolvedSkillPreparationTimeSec":100,"preEvolvedSkillSPCost":200,"skillName":"Combustive Blessing (II)","skillDescription":"Greatly increases the effectiveness of ally fire skills.","skillDurationSec":110,"skillPreparationTimeSec":90,"skillSPCost":200}},{"name":"Ogre","mstId":773,"resourceName":"0773","rarity":6,"isEvolvable":true,"skill":{"preEvolvedSkillName":"Defiant Roar (II)","preEvolvedSkillDescription":"Greatly increases the effectiveness of all vanguard ally attack skills.\\nEffective only when at a disadvantage during a combo chance.","preEvolvedSkillDurationSec":110,"preEvolvedSkillPreparationTimeSec":70,"preEvolvedSkillSPCost":200,"skillName":"Defiant Roar (III)","skillDescription":"Massively increases the effectiveness of all vanguard ally skills.\\nEffective only when at a disadvantage during a combo chance.","skillDurationSec":120,"skillPreparationTimeSec":60,"skillSPCost":200}},{"name":"Simone","mstId":825,"resourceName":"0825","rarity":6,"isEvolvable":true,"skill":{"preEvolvedSkillName":"Fairy King Magic (I)","preEvolvedSkillDescription":"Reduces the SP cost of all ally skills.","preEvolvedSkillDurationSec":100,"preEvolvedSkillPreparationTimeSec":80,"preEvolvedSkillSPCost":200,"skillName":"Fairy King Magic (II)","skillDescription":"Greatly reduces the SP cost of ally skills of any affinity.","skillDurationSec":110,"skillPreparationTimeSec":70,"skillSPCost":200}},{"name":"Machine Lifeform","mstId":827,"resourceName":"0827","rarity":4,"isEvolvable":false,"skill":{"skillName":"Engulfing Shout (I)","skillDescription":"Reduces the effectiveness of enemy fire skills.\\nThis summon skill ends when your lifeforce drops below half of that of the enemy.","skillDurationSec":80,"skillPreparationTimeSec":70,"skillSPCost":200}},{"name":"Machine Lifeform (Gun)","mstId":829,"resourceName":"0829","rarity":4,"isEvolvable":false,"skill":{"skillName":"Uplifting Chant (I)","skillDescription":"Increases the activation rate of all ally support skills.","skillDurationSec":100,"skillPreparationTimeSec":100,"skillSPCost":200}},{"name":"Cecilia, the Crimson Banisher","mstId":979,"resourceName":"0979","rarity":6,"isEvolvable":true,"skill":{"preEvolvedSkillName":"Victorious Melody (II)","preEvolvedSkillDescription":"Greatly increases ATK of all surviving allies in the vanguard.\\nApplies to both P.ATK and M.ATK.","preEvolvedSkillDurationSec":0,"preEvolvedSkillPreparationTimeSec":60,"preEvolvedSkillSPCost":0,"skillName":"Victorious Melody (III)","skillDescription":"Massively increases ATK of all surviving allies in the vanguard.\\nApplies to both P.ATK and M.ATK.","skillDurationSec":0,"skillPreparationTimeSec":50,"skillSPCost":0}},{"name":"Library Wisp","mstId":1107,"resourceName":"1107","rarity":6,"isEvolvable":true,"skill":{"preEvolvedSkillName":"Blessed Armor (II)","preEvolvedSkillDescription":"Greatly increases DEF of all surviving allies in the vanguard.\\nApplies to both P.DEF and M.DEF.","preEvolvedSkillDurationSec":0,"preEvolvedSkillPreparationTimeSec":60,"preEvolvedSkillSPCost":0,"skillName":"Blessed Armor (III)","skillDescription":"Massively increases DEF of all surviving allies in the vanguard.\\nApplies to both P.DEF and M.DEF.","skillDurationSec":0,"skillPreparationTimeSec":50,"skillSPCost":0}},{"name":"Lammy","mstId":1915,"resourceName":"1915","rarity":5,"isEvolvable":true,"skill":{"preEvolvedSkillName":"Magical Torrent (I)","preEvolvedSkillDescription":"Recover 5% of all ally SP.","preEvolvedSkillDurationSec":0,"preEvolvedSkillPreparationTimeSec":60,"preEvolvedSkillSPCost":200,"skillName":"Magical Torrent (II)","skillDescription":"Recover 15% of all ally SP.","skillDurationSec":0,"skillPreparationTimeSec":50,"skillSPCost":200}},{"name":"Sea Snail","mstId":1917,"resourceName":"1917","rarity":5,"isEvolvable":true,"skill":{"preEvolvedSkillName":"Wall Sacrifice (I)","preEvolvedSkillDescription":"Increases M.DEF of all surviving allies in the vanguard.","preEvolvedSkillDurationSec":0,"preEvolvedSkillPreparationTimeSec":90,"preEvolvedSkillSPCost":200,"skillName":"Wall Sacrifice (II)","skillDescription":"Greatly increases M.DEF of all surviving allies in the vanguard.","skillDurationSec":0,"skillPreparationTimeSec":80,"skillSPCost":200}},{"name":"Karkinos","mstId":1929,"resourceName":"1929","rarity":6,"isEvolvable":true,"skill":{"preEvolvedSkillName":"Blessed Armor (II)","preEvolvedSkillDescription":"Greatly increases DEF of all surviving allies in the vanguard.\\nApplies to both P.DEF and M.DEF.","preEvolvedSkillDurationSec":0,"preEvolvedSkillPreparationTimeSec":60,"preEvolvedSkillSPCost":0,"skillName":"Blessed Armor (III)","skillDescription":"Massively increases DEF of all surviving allies in the vanguard.\\nApplies to both P.DEF and M.DEF.","skillDurationSec":0,"skillPreparationTimeSec":50,"skillSPCost":0}},{"name":"Disembodied Emil","mstId":2218,"resourceName":"2218","rarity":6,"isEvolvable":true,"skill":{"preEvolvedSkillName":"False Blade (II)","preEvolvedSkillDescription":"Greatly increases P.ATK of surviving allies in the vanguard.","preEvolvedSkillDurationSec":0,"preEvolvedSkillPreparationTimeSec":80,"preEvolvedSkillSPCost":200,"skillName":"False Blade (III)","skillDescription":"Massively increases P.ATK of surviving allies in the vanguard.","skillDurationSec":0,"skillPreparationTimeSec":70,"skillSPCost":200}},{"name":"Shadowlord","mstId":2975,"resourceName":"2975","rarity":6,"isEvolvable":true,"skill":{"preEvolvedSkillName":"For Whom The Bell Splashes (I)","preEvolvedSkillDescription":"Increases the effectiveness of water weapon skills, but also increases enemy wind damage.","preEvolvedSkillDurationSec":80,"preEvolvedSkillPreparationTimeSec":70,"preEvolvedSkillSPCost":200,"skillName":"For Whom The Bell Splashes (II)","skillDescription":"Greatly increases the effectiveness of water weapon skills, but also increases enemy wind damage.","skillDurationSec":90,"skillPreparationTimeSec":60,"skillSPCost":200}},{"name":"Girl","mstId":2977,"resourceName":"2977","rarity":6,"isEvolvable":true,"skill":{"preEvolvedSkillName":"Song of Betrayal (I)","preEvolvedSkillDescription":"Increases P.ATK and M.ATK of surviving allies in the front row.\\nIf there is an ATK debuff effective, effect will be increased according to the reduction.","preEvolvedSkillDurationSec":0,"preEvolvedSkillPreparationTimeSec":70,"preEvolvedSkillSPCost":200,"skillName":"Song of Betrayal (II)","skillDescription":"Greatly increases P.ATK and M.ATK of surviving allies in the vanguard.\\nIf there is an ATK debuff effective, effect will be increased according to the reduction.","skillDurationSec":0,"skillPreparationTimeSec":60,"skillSPCost":200}},{"name":"Swift Soldier","mstId":2989,"resourceName":"2989","rarity":5,"isEvolvable":true,"skill":{"preEvolvedSkillName":"Armor of Lamentation (I)","preEvolvedSkillDescription":"Reduces DEF of all enemies in the vanguard, even if they have fainted.\\nApplies to both P.DEF and M.DEF.","preEvolvedSkillDurationSec":0,"preEvolvedSkillPreparationTimeSec":70,"preEvolvedSkillSPCost":200,"skillName":"Armor of Lamentation (II)","skillDescription":"Greatly reduces DEF of all enemies in the vanguard, even if they have fainted.\\nApplies to both P.DEF and M.DEF.","skillDurationSec":0,"skillPreparationTimeSec":60,"skillSPCost":200}},{"name":"Flying Magician","mstId":2991,"resourceName":"2991","rarity":5,"isEvolvable":true,"skill":{"preEvolvedSkillName":"Tidal Fairy Master (I)","preEvolvedSkillDescription":"Reduces the SP cost of ally water skills.","preEvolvedSkillDurationSec":60,"preEvolvedSkillPreparationTimeSec":60,"preEvolvedSkillSPCost":200,"skillName":"Tidal Fairy Master (II)","skillDescription":"Greatly reduces the SP cost of ally water skills.","skillDurationSec":70,"skillPreparationTimeSec":50,"skillSPCost":200}}]