[{"name":"Staff of Submission","shortName":"Staff of Submission","attribute":1,"mstId":5,"resourceName":"0005","rarity":"S","url":"./assets/img/weapS/0005.png"},{"name":"Monk's Staff","shortName":"Monk's Staff","attribute":1,"mstId":21,"resourceName":"0021","rarity":"S","url":"./assets/img/weapS/0021.png"},{"name":"Risen Staff","shortName":"Risen Staff","attribute":1,"mstId":37,"resourceName":"0037","rarity":"SR","url":"./assets/img/weapSR/0037.png"},{"name":"Scepter of Power","shortName":"Scepter of Power","attribute":1,"mstId":55,"resourceName":"0055","rarity":"A","url":"./assets/img/weapA/0055.png"},{"name":"Apprentice's Staff","shortName":"Apprentice's Staff","attribute":1,"mstId":73,"resourceName":"0073","rarity":"A","url":"./assets/img/weapA/0073.png"},{"name":"Irreconcilable Enemy","shortName":"Irreconcilable Enemy","attribute":1,"mstId":91,"resourceName":"0091","rarity":"SR","url":"./assets/img/weapSR/0091.png"},{"name":"Staff of Bondage","shortName":"Staff of Bondage","attribute":2,"mstId":107,"resourceName":"0107","rarity":"SR","url":"./assets/img/weapSR/0107.png"},{"name":"Engraved Blue Staff","shortName":"Engraved Blue Staff","attribute":2,"mstId":119,"resourceName":"0119","rarity":"S","url":"./assets/img/weapS/0119.png"},{"name":"Sands of Time","shortName":"Sands of Time","attribute":3,"mstId":135,"resourceName":"0135","rarity":"S","url":"./assets/img/weapS/0135.png"},{"name":"Devilish Staff","shortName":"Devilish Staff","attribute":2,"mstId":156,"resourceName":"0156","rarity":"A","url":"./assets/img/weapA/0156.png"},{"name":"Staff of Insanity","shortName":"Staff of Insanity","attribute":2,"mstId":175,"resourceName":"0175","rarity":"A","url":"./assets/img/weapA/0175.png"},{"name":"Naive Miracle Staff","shortName":"Naive Miracle Staff","attribute":2,"mstId":193,"resourceName":"0193","rarity":"SR","url":"./assets/img/weapSR/0193.png"},{"name":"Staff of Masochism","shortName":"Staff of Masochism","attribute":2,"mstId":207,"resourceName":"0207","rarity":"S","url":"./assets/img/weapS/0207.png"},{"name":"Cumbersome Staff","shortName":"Cumbersome Staff","attribute":3,"mstId":223,"resourceName":"0223","rarity":"S","url":"./assets/img/weapS/0223.png"},{"name":"Ginger Sage (Part I)","shortName":"Ginger Sage (Part I)","attribute":3,"mstId":242,"resourceName":"0242","rarity":"SR","url":"./assets/img/weapSR/0242.png"},{"name":"White Lightning Staff","shortName":"White Lightning Staf","attribute":3,"mstId":265,"resourceName":"0265","rarity":"A","url":"./assets/img/weapA/0265.png"},{"name":"Staff of the Wise","shortName":"Staff of the Wise","attribute":3,"mstId":281,"resourceName":"0281","rarity":"A","url":"./assets/img/weapA/0281.png"},{"name":"Ginger Sage (Part II)","shortName":"Ginger Sage (Part II","attribute":3,"mstId":295,"resourceName":"0295","rarity":"SR","url":"./assets/img/weapSR/0295.png"},{"name":"Reincarnation","shortName":"Reincarnation","attribute":2,"mstId":317,"resourceName":"0317","rarity":"S","url":"./assets/img/weapS/0317.png"},{"name":"Oblivion Staff","shortName":"Oblivion Staff","attribute":3,"mstId":335,"resourceName":"0335","rarity":"SR","url":"./assets/img/weapSR/0335.png"},{"name":"Staff of Incarnation","shortName":"Staff of Incarnation","attribute":3,"mstId":353,"resourceName":"0353","rarity":"SR","url":"./assets/img/weapSR/0353.png"},{"name":"Deep Sea Staff","shortName":"Deep Sea Staff","attribute":1,"mstId":641,"resourceName":"0641","rarity":"SR","url":"./assets/img/weapSR/0641.png"},{"name":"Proof of Virtue","shortName":"Proof of Virtue","attribute":3,"mstId":657,"resourceName":"0657","rarity":"S","url":"./assets/img/weapS/0657.png"},{"name":"Proof of Hypocrisy","shortName":"Proof of Hypocrisy","attribute":2,"mstId":689,"resourceName":"0689","rarity":"S","url":"./assets/img/weapS/0689.png"},{"name":"Ebony Staff","shortName":"Ebony Staff","attribute":1,"mstId":751,"resourceName":"0751","rarity":"SR","url":"./assets/img/weapSR/0751.png"},{"name":"Clairvoyant Staff","shortName":"Clairvoyant Staff","attribute":1,"mstId":763,"resourceName":"0763","rarity":"S","url":"./assets/img/weapS/0763.png"},{"name":"Black Iron Staff","shortName":"Black Iron Staff","attribute":2,"mstId":779,"resourceName":"0779","rarity":"SR","url":"./assets/img/weapSR/0779.png"},{"name":"Forbidden Staff","shortName":"Forbidden Staff","attribute":3,"mstId":805,"resourceName":"0805","rarity":"S","url":"./assets/img/weapS/0805.png"},{"name":"No. 7's Staff","shortName":"No. 7's Staff","attribute":2,"mstId":817,"resourceName":"0817","rarity":"SR","url":"./assets/img/weapSR/0817.png"},{"name":"Golden Staff","shortName":"Golden Staff","attribute":2,"mstId":987,"resourceName":"0987","rarity":"SR","url":"./assets/img/weapSR/0987.png"},{"name":"Bell Staff","shortName":"Bell Staff","attribute":1,"mstId":995,"resourceName":"0995","rarity":"SR","url":"./assets/img/weapSR/0995.png"},{"name":"Spider Web Staff","shortName":"Spider Web Staff","attribute":3,"mstId":1033,"resourceName":"1033","rarity":"SR","url":"./assets/img/weapSR/1033.png"},{"name":"Staff of Retrogression","shortName":"Staff of Retrogressi","attribute":1,"mstId":1041,"resourceName":"1041","rarity":"S","url":"./assets/img/weapS/1041.png"},{"name":"White Staff of Justice","shortName":"White Staff of Justi","attribute":2,"mstId":1073,"resourceName":"1073","rarity":"SR","url":"./assets/img/weapSR/1073.png"},{"name":"Entrails of Justice","shortName":"Entrails of Justice","attribute":1,"mstId":1097,"resourceName":"1097","rarity":"SR","url":"./assets/img/weapSR/1097.png"},{"name":"Shell Staff","shortName":"Shell Staff","attribute":2,"mstId":1101,"resourceName":"1101","rarity":"SR","url":"./assets/img/weapSR/1101.png"},{"name":"Forest Aid","shortName":"Forest Aid","attribute":3,"mstId":1119,"resourceName":"1119","rarity":"S","url":"./assets/img/weapS/1119.png"},{"name":"Corpse Staff","shortName":"Corpse Staff","attribute":2,"mstId":1149,"resourceName":"1149","rarity":"SR","url":"./assets/img/weapSR/1149.png"},{"name":"Staff of Delusion","shortName":"Staff of Delusion","attribute":1,"mstId":1155,"resourceName":"1155","rarity":"SR","url":"./assets/img/weapSR/1155.png"},{"name":"Big Talk","shortName":"Big Talk","attribute":1,"mstId":1309,"resourceName":"1309","rarity":"S","url":"./assets/img/weapS/1309.png"},{"name":"Pagan Staff","shortName":"Pagan Staff","attribute":3,"mstId":1364,"resourceName":"1364","rarity":"SR","url":"./assets/img/weapSR/1364.png"},{"name":"Staff of Succession","shortName":"Staff of Succession","attribute":2,"mstId":1392,"resourceName":"1392","rarity":"SR","url":"./assets/img/weapSR/1392.png"},{"name":"Water Emperor's Staff","shortName":"Water Emperor's Staf","attribute":2,"mstId":1424,"resourceName":"1424","rarity":"S","url":"./assets/img/weapS/1424.png"},{"name":"Staff of Deep Prayer","shortName":"Staff of Deep Prayer","attribute":2,"mstId":1456,"resourceName":"1456","rarity":"SR","url":"./assets/img/weapSR/1456.png"},{"name":"One's Beloved Staff","shortName":"One's Beloved Staff","attribute":3,"mstId":1472,"resourceName":"1472","rarity":"SR","url":"./assets/img/weapSR/1472.png"},{"name":"Blessing Staff","shortName":"Blessing Staff","attribute":2,"mstId":1911,"resourceName":"1911","rarity":"SR","url":"./assets/img/weapSR/1911.png"},{"name":"Masochism's Intent","shortName":"Masochism's Intent","attribute":2,"mstId":2206,"resourceName":"2206","rarity":"SR","url":"./assets/img/weapSR/2206.png"},{"name":"Invader's Staff of Masochism","shortName":"Invader's Staff of M","attribute":2,"mstId":2502,"resourceName":"2502","rarity":"SR","url":"./assets/img/weapSR/2502.png"},{"name":"Devola & Popola's Staff","shortName":"Devola & Popola's St","attribute":3,"mstId":3099,"resourceName":"3099","rarity":"SR","url":"./assets/img/weapSR/3099.png"},{"name":"Origin of Venom","shortName":"Origin of Venom","attribute":3,"mstId":4442,"resourceName":"4442","rarity":"SR","url":"./assets/img/weapSR/4442.png"},{"name":"Staff of Piety","shortName":"Staff of Piety","attribute":3,"mstId":900008,"resourceName":"900008","rarity":"SR","url":"./assets/img/weapSR/900008.png"}]