[{"name":"Meat Pulverizer","skillid":1277,"weaponid":11,"attribute":"Fire","type":"Hammer","url":"/assets/img/weapSR/CardS0011.png"},{"name":"Grudge Hammer","skillid":594,"weaponid":27,"attribute":"Fire","type":"Hammer","url":"/assets/img/weapSR/CardS0027.png"},{"name":"Retainer's Hammer","skillid":606,"weaponid":43,"attribute":"Fire","type":"Hammer","url":"/assets/img/weapSR/CardS0043.png"},{"name":"Strongman's Hammer","skillid":1239,"weaponid":61,"attribute":"Fire","type":"Hammer","url":"/assets/img/weapA/0061.png"},{"name":"Assassin's Kit","skillid":1244,"weaponid":79,"attribute":"Fire","type":"Hammer","url":"/assets/img/weapA/0079.png"},{"name":"Warden's Mallet","skillid":1334,"weaponid":97,"attribute":"Fire","type":"Hammer","url":"/assets/img/weapSR/CardS0097.png"},{"name":"Soul Shell","skillid":3265,"weaponid":113,"attribute":"Water","type":"Hammer","url":"/assets/img/weapSR/CardS0113.png"},{"name":"Revolutionary's Maul","skillid":1283,"weaponid":125,"attribute":"Water","type":"Hammer","url":"/assets/img/weapSR/CardS0125.png"},{"name":"Death and Agony","skillid":619,"weaponid":141,"attribute":"Water","type":"Hammer","url":"/assets/img/weapSR/CardS0141.png"},{"name":"Oblivion's Intent","skillid":1250,"weaponid":165,"attribute":"Water","type":"Hammer","url":"/assets/img/weapA/0165.png"},{"name":"Maul of Carnage","skillid":1250,"weaponid":181,"attribute":"Water","type":"Hammer","url":"/assets/img/weapA/0181.png"},{"name":"The Lord's Hammer","skillid":3261,"weaponid":199,"attribute":"Water","type":"Hammer","url":"/assets/img/weapSR/CardS0199.png"},{"name":"Waking Nightmare","skillid":1288,"weaponid":213,"attribute":"Wind","type":"Hammer","url":"/assets/img/weapSR/CardS0213.png"},{"name":"Death's Remains","skillid":1292,"weaponid":229,"attribute":"Wind","type":"Hammer","url":"/assets/img/weapSR/CardS0229.png"},{"name":"Gluttonous God's Rod","skillid":608,"weaponid":248,"attribute":"Wind","type":"Hammer","url":"/assets/img/weapSR/CardS0248.png"},{"name":"Hammer of Brutality","skillid":1261,"weaponid":269,"attribute":"Wind","type":"Hammer","url":"/assets/img/weapA/0269.png"},{"name":"Oracle Knight's Axe","skillid":1261,"weaponid":287,"attribute":"Wind","type":"Hammer","url":"/assets/img/weapA/0287.png"},{"name":"Hammer of Endtimes","skillid":998,"weaponid":301,"attribute":"Wind","type":"Hammer","url":"/assets/img/weapSR/CardS0301.png"},{"name":"Veteran's Mallet","skillid":1297,"weaponid":327,"attribute":"Fire","type":"Hammer","url":"/assets/img/weapSR/CardS0327.png"},{"name":"Mad Demon","skillid":1288,"weaponid":341,"attribute":"Wind","type":"Hammer","url":"/assets/img/weapSR/CardS0341.png"},{"name":"Hammer of Justice","skillid":998,"weaponid":581,"attribute":"Wind","type":"Hammer","url":"/assets/img/weapSR/CardS0581.png"},{"name":"Magma Axe","skillid":1277,"weaponid":651,"attribute":"Fire","type":"Hammer","url":"/assets/img/weapSR/CardS0651.png"},{"name":"Mechanical Hammer","skillid":3265,"weaponid":675,"attribute":"Water","type":"Hammer","url":"/assets/img/weapSR/CardS0675.png"},{"name":"Steel Star","skillid":1292,"weaponid":683,"attribute":"Wind","type":"Hammer","url":"/assets/img/weapSR/CardS0683.png"},{"name":"Axe of Paranoia","skillid":1283,"weaponid":757,"attribute":"Water","type":"Hammer","url":"/assets/img/weapSR/CardS0757.png"},{"name":"Hammer of Depravity","skillid":1664,"weaponid":799,"attribute":"Fire","type":"Hammer","url":"/assets/img/weapSR/CardS0799.png"},{"name":"Iron Pipe","skillid":619,"weaponid":819,"attribute":"Water","type":"Hammer","url":"/assets/img/weapSR/CardS0819.png"},{"name":"Beastlord","skillid":3271,"weaponid":927,"attribute":"Water","type":"Hammer","url":"/assets/img/weapSR/CardS0927.png"},{"name":"Ancestral Double Axe","skillid":1288,"weaponid":1001,"attribute":"Wind","type":"Hammer","url":"/assets/img/weapSR/CardS1001.png"},{"name":"Silver Axe","skillid":3267,"weaponid":1017,"attribute":"Water","type":"Hammer","url":"/assets/img/weapSR/CardS1017.png"},{"name":"Giant's Right Hand","skillid":1768,"weaponid":1037,"attribute":"Wind","type":"Hammer","url":"/assets/img/weapSR/CardS1037.png"},{"name":"Hammer of Delusion","skillid":3261,"weaponid":1049,"attribute":"Water","type":"Hammer","url":"/assets/img/weapSR/CardS1049.png"},{"name":"Enchanting Hammer","skillid":619,"weaponid":1063,"attribute":"Water","type":"Hammer","url":"/assets/img/weapSR/CardS1063.png"},{"name":"Brutality's Tool","skillid":1334,"weaponid":1075,"attribute":"Fire","type":"Hammer","url":"/assets/img/weapSR/CardS1075.png"},{"name":"Mallet of Dependence","skillid":1768,"weaponid":1079,"attribute":"Wind","type":"Hammer","url":"/assets/img/weapSR/CardS1079.png"},{"name":"Pagan Bludgeon","skillid":2002,"weaponid":1115,"attribute":"Fire","type":"Hammer","url":"/assets/img/weapSR/CardS1115.png"},{"name":"Torturous Mallet","skillid":606,"weaponid":1135,"attribute":"Fire","type":"Hammer","url":"/assets/img/weapSR/CardS1135.png"},{"name":"Flail of Masochism","skillid":2095,"weaponid":1299,"attribute":"Wind","type":"Hammer","url":"/assets/img/weapSR/CardS1299.png"},{"name":"Black Iron Hammer","skillid":3268,"weaponid":1341,"attribute":"Water","type":"Hammer","url":"/assets/img/weapSR/CardS1341.png"},{"name":"Brutal Intent","skillid":2141,"weaponid":1362,"attribute":"Fire","type":"Hammer","url":"/assets/img/weapSR/CardS1362.png"},{"name":"Treasure Rod","skillid":2167,"weaponid":1378,"attribute":"Wind","type":"Hammer","url":"/assets/img/weapSR/CardS1378.png"},{"name":"The Emperor's Hegemony","skillid":3266,"weaponid":1384,"attribute":"Water","type":"Hammer","url":"/assets/img/weapSR/CardS1384.png"},{"name":"Giant's Hand Axe","skillid":2173,"weaponid":1394,"attribute":"Fire","type":"Hammer","url":"/assets/img/weapSR/CardS1394.png"},{"name":"Oar Hammer","skillid":1283,"weaponid":1402,"attribute":"Water","type":"Hammer","url":"/assets/img/weapSR/CardS1402.png"},{"name":"Lion Killer's Iron Hammer","skillid":1283,"weaponid":1420,"attribute":"Water","type":"Hammer","url":"/assets/img/weapSR/CardS1420.png"},{"name":"Intent of Curiosity","skillid":2254,"weaponid":1452,"attribute":"Fire","type":"Hammer","url":"/assets/img/weapSR/CardS1452.png"},{"name":"Senhime's Great Axe","skillid":2253,"weaponid":1468,"attribute":"Fire","type":"Hammer","url":"/assets/img/weapSR/CardS1468.png"},{"name":"Flag of a Ruined Country","skillid":3264,"weaponid":1558,"attribute":"Water","type":"Hammer","url":"/assets/img/weapSR/CardS1558.png"},{"name":"Axe of Ruin","skillid":608,"weaponid":1568,"attribute":"Wind","type":"Hammer","url":"/assets/img/weapSR/CardS1568.png"},{"name":"Instrument Artisan's Flail","skillid":2173,"weaponid":1576,"attribute":"Fire","type":"Hammer","url":"/assets/img/weapSR/CardS1576.png"},{"name":"War Axe of Wicked Love","skillid":2390,"weaponid":1604,"attribute":"Fire","type":"Hammer","url":"/assets/img/weapSR/CardS1604.png"},{"name":"Beast Axe","skillid":998,"weaponid":1620,"attribute":"Wind","type":"Hammer","url":"/assets/img/weapSR/CardS1620.png"},{"name":"Shatterer","skillid":2599,"weaponid":1740,"attribute":"Wind","type":"Hammer","url":"/assets/img/weapSR/CardS1740.png"},{"name":"Axe of Punishment","skillid":3264,"weaponid":1885,"attribute":"Water","type":"Hammer","url":"/assets/img/weapSR/CardS1885.png"},{"name":"Eagle's Bludgeoner","skillid":2167,"weaponid":1895,"attribute":"Wind","type":"Hammer","url":"/assets/img/weapSR/CardS1895.png"},{"name":"Turbulent Mace","skillid":3268,"weaponid":1907,"attribute":"Water","type":"Hammer","url":"/assets/img/weapSR/CardS1907.png"},{"name":"Rake of Languor","skillid":2615,"weaponid":1919,"attribute":"Wind","type":"Hammer","url":"/assets/img/weapSR/CardS1919.png"},{"name":"Rallying Hammer","skillid":3271,"weaponid":2005,"attribute":"Water","type":"Hammer","url":"/assets/img/weapSR/CardS2005.png"},{"name":"Club of Calming","skillid":2095,"weaponid":2050,"attribute":"Wind","type":"Hammer","url":"/assets/img/weapSR/CardS2050.png"},{"name":"Blast of Demise (Calamity)","skillid":1334,"weaponid":2054,"attribute":"Fire","type":"Hammer","url":"/assets/img/weapSR/CardS2054.png"},{"name":"Iron Ball of Misery","skillid":3271,"weaponid":2110,"attribute":"Water","type":"Hammer","url":"/assets/img/weapSR/CardS2110.png"},{"name":"Black Axe of Brutality","skillid":2002,"weaponid":2124,"attribute":"Fire","type":"Hammer","url":"/assets/img/weapSR/CardS2124.png"},{"name":"Shell Axe","skillid":1250,"weaponid":2186,"attribute":"Water","type":"Hammer","url":"/assets/img/weapSR/CardS2186.png"},{"name":"Purifying Blow","skillid":3267,"weaponid":2192,"attribute":"Water","type":"Hammer","url":"/assets/img/weapSR/CardS2192.png"},{"name":"Troublemaker's Cleave","skillid":3267,"weaponid":2212,"attribute":"Water","type":"Hammer","url":"/assets/img/weapSR/CardS2212.png"},{"name":"Battle's Gospel","skillid":3663,"weaponid":2222,"attribute":"Wind","type":"Hammer","url":"/assets/img/weapSR/CardS2222.png"},{"name":"Axe of Bondage","skillid":606,"weaponid":2240,"attribute":"Fire","type":"Hammer","url":"/assets/img/weapSR/CardS2240.png"},{"name":"Club of Rotten Rope","skillid":2599,"weaponid":2338,"attribute":"Wind","type":"Hammer","url":"/assets/img/weapSR/CardS2338.png"},{"name":"Great Axe of Bondage","skillid":3261,"weaponid":2356,"attribute":"Water","type":"Hammer","url":"/assets/img/weapSR/CardS2356.png"},{"name":"Axe of Fierce Battle","skillid":2222,"weaponid":2386,"attribute":"Fire","type":"Hammer","url":"/assets/img/weapSR/CardS2386.png"},{"name":"Changing of the Guard","skillid":1283,"weaponid":2392,"attribute":"Water","type":"Hammer","url":"/assets/img/weapSR/CardS2392.png"},{"name":"Bludgeon of Flames","skillid":2002,"weaponid":2424,"attribute":"Fire","type":"Hammer","url":"/assets/img/weapSR/CardS2424.png"},{"name":"Bludgeon of Curiosity","skillid":608,"weaponid":2428,"attribute":"Wind","type":"Hammer","url":"/assets/img/weapSR/CardS2428.png"},{"name":"Cursed Hammer","skillid":3266,"weaponid":2508,"attribute":"Water","type":"Hammer","url":"/assets/img/weapSR/CardS2508.png"},{"name":"Howling Axe","skillid":2002,"weaponid":2596,"attribute":"Fire","type":"Hammer","url":"/assets/img/weapSR/CardS2596.png"},{"name":"Intent of Dependence","skillid":998,"weaponid":2608,"attribute":"Wind","type":"Hammer","url":"/assets/img/weapSR/CardS2608.png"},{"name":"Axe of the Evil Eye","skillid":3572,"weaponid":2667,"attribute":"Fire","type":"Hammer","url":"/assets/img/weapSR/CardS2667.png"},{"name":"Temple Axe","skillid":2167,"weaponid":2711,"attribute":"Wind","type":"Hammer","url":"/assets/img/weapSR/CardS2711.png"},{"name":"Hammer of Regret","skillid":3265,"weaponid":2777,"attribute":"Water","type":"Hammer","url":"/assets/img/weapSR/CardS2777.png"},{"name":"Flail of Anger (Kageuchi)","skillid":1768,"weaponid":2801,"attribute":"Wind","type":"Hammer","url":"/assets/img/weapSR/CardS2801.png"},{"name":"Axe of Shadows","skillid":3663,"weaponid":2867,"attribute":"Wind","type":"Hammer","url":"/assets/img/weapSR/CardS2867.png"},{"name":"Vile Axe","skillid":1288,"weaponid":2985,"attribute":"Wind","type":"Hammer","url":"/assets/img/weapSR/CardS2985.png"},{"name":"Flamestone Hammer","skillid":1334,"weaponid":3133,"attribute":"Fire","type":"Hammer","url":"/assets/img/weapSR/CardS3133.png"},{"name":"Wrath Hammer (Kageuchi)","skillid":2095,"weaponid":3194,"attribute":"Wind","type":"Hammer","url":"/assets/img/weapSR/CardS3194.png"},{"name":"Fangs of the Centipede King","skillid":2222,"weaponid":3305,"attribute":"Fire","type":"Hammer","url":"/assets/img/weapSR/CardS3305.png"},{"name":"Gravitas Singula","skillid":3261,"weaponid":3379,"attribute":"Water","type":"Hammer","url":"/assets/img/weapSR/CardS3379.png"},{"name":"Birdcall","skillid":3663,"weaponid":3407,"attribute":"Wind","type":"Hammer","url":"/assets/img/weapSR/CardS3407.png"},{"name":"Silver Club of Nouveau Riche","skillid":3863,"weaponid":3508,"attribute":"Wind","type":"Hammer","url":"/assets/img/weapSR/CardS3508.png"},{"name":"Origin of Flames","skillid":606,"weaponid":4438,"attribute":"Fire","type":"Hammer","url":"/assets/img/weapSR/CardS4438.png"},{"name":"Rem's Iron Ball","skillid":608,"weaponid":4695,"attribute":"Wind","type":"Hammer","url":"/assets/img/weapSR/CardS4695.png"},{"name":"Sonic Diva Hammer","skillid":608,"weaponid":5688,"attribute":"Wind","type":"Hammer","url":"/assets/img/weapSR/CardS5688.png"},{"name":"Raging Tides","skillid":2167,"weaponid":5998,"attribute":"Wind","type":"Hammer","url":"/assets/img/weapSR/CardS5998.png"},{"name":"Mallet of Vanity","skillid":2002,"weaponid":6539,"attribute":"Fire","type":"Hammer","url":"/assets/img/weapSR/CardS6539.png"},{"name":"Glass Sphere","skillid":3265,"weaponid":7336,"attribute":"Water","type":"Hammer","url":"/assets/img/weapSR/CardS7336.png"},{"name":"Mark of Loyalty","skillid":1283,"weaponid":7359,"attribute":"Water","type":"Hammer","url":"/assets/img/weapSR/CardS7359.png"},{"name":"Blossom Ice Hammer","skillid":3267,"weaponid":9069,"attribute":"Water","type":"Hammer","url":"/assets/img/weapSR/CardS9069.png"},{"name":"Club of a Tragic Wind","skillid":3261,"weaponid":9075,"attribute":"Water","type":"Hammer","url":"/assets/img/weapSR/CardS9075.png"},{"name":"Knighthood Club","skillid":2390,"weaponid":900012,"attribute":"Fire","type":"Hammer","url":"/assets/img/weapSR/CardS900012.png"},{"name":"Axe of Masochism","skillid":608,"weaponid":900020,"attribute":"Wind","type":"Hammer","url":"/assets/img/weapSR/CardS900020.png"},{"name":"Hauyne Mallet","skillid":3266,"weaponid":900028,"attribute":"Water","type":"Hammer","url":"/assets/img/weapSR/CardS900028.png"},{"name":"Ancient City Dream","skillid":606,"weaponid":900032,"attribute":"Fire","type":"Hammer","url":"/assets/img/weapSR/CardS900032.png"},{"name":"Misery's End","skillid":3265,"weaponid":900040,"attribute":"Water","type":"Hammer","url":"/assets/img/weapSR/CardS900040.png"},{"name":"Palace Club","skillid":3266,"weaponid":900046,"attribute":"Water","type":"Hammer","url":"/assets/img/weapSR/CardS900046.png"},{"name":"Peacebringer’s Oath","skillid":4291,"weaponid":900068,"attribute":"Water","type":"Hammer","url":"/assets/img/weapSR/CardS900068.png"}]